{
  "@context": "http://www.shared-canvas.org/ns/context.json",
  "@type": "sc:AnnotationList",
  "@id": "https://dms-data.stanford.edu/data/manifests/Parker/qt729hp8274/list/3v.json",
  "resources": [
    {
      "@id": "https://dms-data.stanford.edu/data/manifests/Parker/qt729hp8274/annotation/dbb50db0-8d31-47cd-838e-932f6c569cce",
      "@type": "oa:annotation",
      "motivation": "oa:commenting",
      "on": "https://dms-data.stanford.edu/data/manifests/Parker/qt729hp8274/canvas/canvas-6#xywh=0,0,5302,6596",
      "resource": {
        "@id": "https://dms-data.stanford.edu/data/manifests/Parker/qt729hp8274/res/3133694e-c75a-41ed-be8a-eaa0994aa782",
        "@type": "cnt:ContentAsText",
        "format": "text/plain",
        "chars": "June has a good many additions (xiii). Original entries are 5. Bonefacii Archiepiscopi et Martiris Botulfi 20. Crispini Martiris Albani Etheldride"
      }
    }
  ]
}
