{
  "@context": "http://www.shared-canvas.org/ns/context.json",
  "@type": "sc:AnnotationList",
  "@id": "https://dms-data.stanford.edu/data/manifests/Parker/qt808nj0703/list/65v.json",
  "resources": [
    {
      "@id": "https://dms-data.stanford.edu/data/manifests/Parker/qt808nj0703/annotation/7394cad5-5cbb-4709-ba51-28604f1f4532",
      "@type": "oa:annotation",
      "motivation": "oa:commenting",
      "on": "https://dms-data.stanford.edu/data/manifests/Parker/qt808nj0703/canvas/canvas-138#xywh=0,0,5844,8648",
      "resource": {
        "@id": "https://dms-data.stanford.edu/data/manifests/Parker/qt808nj0703/res/eb8ad195-8a6e-47a7-8c9c-3c3be8cc798d",
        "@type": "cnt:ContentAsText",
        "format": "text/plain",
        "chars": "A maiden on L. with book. A prostrate man: a devil on R. seizes his leg. Miracle of a girl delivered from a demon"
      }
    }
  ]
}
