{
  "@context": "http://www.shared-canvas.org/ns/context.json",
  "@type": "sc:AnnotationList",
  "@id": "https://dms-data.stanford.edu/data/manifests/Parker/th313vp6557/list/7.json",
  "resources": [
    {
      "@id": "https://dms-data.stanford.edu/data/manifests/Parker/th313vp6557/annotation/4f3cbf3f-7d94-4438-9273-42d65550b834",
      "@type": "oa:Annotation",
      "motivation": "oa:commenting",
      "on": "https://dms-data.stanford.edu/data/manifests/Parker/th313vp6557/canvas/canvas-19#xywh=0,0,4971,8290",
      "resource": {
        "@id": "https://dms-data.stanford.edu/data/manifests/Parker/th313vp6557/res/003d25e1-8f5c-428f-9133-fb1a9e16ecff",
        "@type": "cnt:ContentAsText",
        "format": "text/plain",
        "chars": "May 3. Added in purple, Obitus Sæburge 7. In brittannia Sancti Iohannis episcopi 15. Added, Obitus Sæƿulfi laici patris Clementis 16. Added, Obitus Colemanni cog. W... 17. Added, Obitus Ærnulfi l[aici] 19. Capitals, Dunstani 20. Æthelberhti martyris 26. Capitals, Augustini anglorum episcopi"
      }
    }
  ]
}
