{
    "@context": "http://www.shared-canvas.org/ns/context.json", 
    "@id": "http://dms-data.stanford.edu/data/manifests/Parker/ft757ht3699/list/text-p458.json", 
    "@type": "sc:AnnotationList", 
    "resources": [
        {
            "@id": "_:N1f12304ee4ad45a08fd79af7150986bc", 
            "@type": "oa:Annotation", 
            "motivation": "sc:painting", 
            "resource": {
                "@id": "9b03629a4d5e0965ebb671040c32639b", 
                "@type": "cnt:ContentAsText", 
                "format": "text/plain", 
                "chars": "to ondr\u00e6denne \u00feonne to trahtnigenne; \u00feam rican <lb/>", 
                "language": "ang"
            }, 
            "on": "http://dms-data.stanford.edu/data/manifests/Parker/ft757ht3699/canvas/canvas-476#xywh=811,223,2717,152"
        }, 
        {
            "@id": "_:N71ae5060d73b4ed49e5b8bfeaa727cea", 
            "@type": "oa:Annotation", 
            "motivation": "sc:painting", 
            "resource": {
                "@id": "bebf621be81a68fd29d089d9812e8a20", 
                "@type": "cnt:ContentAsText", 
                "format": "text/plain", 
                "chars": "w\u00e6s forgolden mid \u00feam hwilwendlicum spedum{\u00e6htu<m>} gif <lb/>", 
                "language": "ang"
            }, 
            "on": "http://dms-data.stanford.edu/data/manifests/Parker/ft757ht3699/canvas/canvas-476#xywh=811,375,2717,196"
        }, 
        {
            "@id": "_:N1ae3cf41e5394d1fbb4bea9eb16d79ef", 
            "@type": "oa:Annotation", 
            "motivation": "sc:painting", 
            "resource": {
                "@id": "0d05255527ee9bbe78be579ed48a22f6", 
                "@type": "cnt:ContentAsText", 
                "format": "text/plain", 
                "chars": "he hw\u00e6t to go*de gefremode. [et] \u00feam \u00feearfan w\u00e6s forgol<lb/>", 
                "language": "ang"
            }, 
            "on": "http://dms-data.stanford.edu/data/manifests/Parker/ft757ht3699/canvas/canvas-476#xywh=811,571,2717,185"
        }, 
        {
            "@id": "_:N86e51ef60dce4106b5faeb2287e59f0c", 
            "@type": "oa:Annotation", 
            "motivation": "sc:painting", 
            "resource": {
                "@id": "75da97574a48575cadbed946affde5a4", 
                "@type": "cnt:ContentAsText", 
                "format": "text/plain", 
                "chars": "den mid \u00fe\u00e6re yrm\u00f0e. gyf he hw\u00e6t to yfele gedyde; <lb/>", 
                "language": "ang"
            }, 
            "on": "http://dms-data.stanford.edu/data/manifests/Parker/ft757ht3699/canvas/canvas-476#xywh=811,756,2717,157"
        }, 
        {
            "@id": "_:N8b1b33e8127146999217621025a6bad8", 
            "@type": "oa:Annotation", 
            "motivation": "sc:painting", 
            "resource": {
                "@id": "22dd5764e79016211ee5d4acef99fdd9", 
                "@type": "cnt:ContentAsText", 
                "format": "text/plain", 
                "chars": "\u00fea underfeng se welega his ges\u00e6l\u00fea to edleane to <lb/>", 
                "language": "ang"
            }, 
            "on": "http://dms-data.stanford.edu/data/manifests/Parker/ft757ht3699/canvas/canvas-476#xywh=811,914,2717,201"
        }, 
        {
            "@id": "_:Nda85f896416c492f8df65ebdff4c42dd", 
            "@type": "oa:Annotation", 
            "motivation": "sc:painting", 
            "resource": {
                "@id": "9efde56701f5b882f00a392bdc5bd7f5", 
                "@type": "cnt:ContentAsText", 
                "format": "text/plain", 
                "chars": "sceortum bryce. [et] \u00fe\u00e6s \u00feearfan hafenleast acl\u00e6n<lb/>", 
                "language": "ang"
            }, 
            "on": "http://dms-data.stanford.edu/data/manifests/Parker/ft757ht3699/canvas/canvas-476#xywh=811,1116,2717,196"
        }, 
        {
            "@id": "_:Nfc2a10729fee4e0b9af4ce6d57aa466e", 
            "@type": "oa:Annotation", 
            "motivation": "sc:painting", 
            "resource": {
                "@id": "850c188ddf5d0fdca2cb95520250b213", 
                "@type": "cnt:ContentAsText", 
                "format": "text/plain", 
                "chars": "sode his lytlan gyltas; hyne geswencte seo w\u00e6dlung. <lb/>", 
                "language": "ang"
            }, 
            "on": "http://dms-data.stanford.edu/data/manifests/Parker/ft757ht3699/canvas/canvas-476#xywh=811,1312,2717,196"
        }, 
        {
            "@id": "_:N30805e1a8b594f22a1ea4e8670943800", 
            "@type": "oa:Annotation", 
            "motivation": "sc:painting", 
            "resource": {
                "@id": "1819fdcff3b5f4e4143c30b5cc76b7c3", 
                "@type": "cnt:ContentAsText", 
                "format": "text/plain", 
                "chars": "[et] afeormode; \u00feone o\u00f0erne gewelgode his genihtsu<m><lb/>", 
                "language": "ang"
            }, 
            "on": "http://dms-data.stanford.edu/data/manifests/Parker/ft757ht3699/canvas/canvas-476#xywh=811,1508,2717,196"
        }, 
        {
            "@id": "_:N72c85074b8be4aa3821f7dbed76fcf85", 
            "@type": "oa:Annotation", 
            "motivation": "sc:painting", 
            "resource": {
                "@id": "b889a8b00324d86f11459f9b8113b667", 
                "@type": "cnt:ContentAsText", 
                "format": "text/plain", 
                "chars": "nys. [et] bep\u00e6hte; ^Gregori<us> cw\u00e6\u00f0.^ Ic bidde eow~ ne forseo ge godes \u00feearfan. <lb/>", 
                "language": "ang"
            }, 
            "on": "http://dms-data.stanford.edu/data/manifests/Parker/ft757ht3699/canvas/canvas-476#xywh=811,1704,2717,212"
        }, 
        {
            "@id": "_:N04f6284ee8e7438699e05365608168cc", 
            "@type": "oa:Annotation", 
            "motivation": "sc:painting", 
            "resource": {
                "@id": "762889a04a2c0ac10ffb796e88b5cbb2", 
                "@type": "cnt:ContentAsText", 
                "format": "text/plain", 
                "chars": "\u00feeah \u00fee hi tallice hw\u00e6t lytles gefremmon. for \u00f0an \u00f0e <lb/>", 
                "language": "ang"
            }, 
            "on": "http://dms-data.stanford.edu/data/manifests/Parker/ft757ht3699/canvas/canvas-476#xywh=811,1916,2717,196"
        }, 
        {
            "@id": "_:N155c3c7f665f443087b4743a0d7659f2", 
            "@type": "oa:Annotation", 
            "motivation": "sc:painting", 
            "resource": {
                "@id": "6951a68ff1e128026d32fe44dd91f65c", 
                "@type": "cnt:ContentAsText", 
                "format": "text/plain", 
                "chars": "heora yrm\u00f0 afeorma\u00f0. \u00fe<\u00e6t> \u00fe<\u00e6t> seo gehw\u00e6de oferflowed<lb/>", 
                "language": "ang"
            }, 
            "on": "http://dms-data.stanford.edu/data/manifests/Parker/ft757ht3699/canvas/canvas-476#xywh=811,2113,2717,196"
        }, 
        {
            "@id": "_:N57126f3ea5fd46ea9b483e0bead57df9", 
            "@type": "oa:Annotation", 
            "motivation": "sc:painting", 
            "resource": {
                "@id": "86f302dbecda5e8fb7fd462928e5ddd8", 
                "@type": "cnt:ContentAsText", 
                "format": "text/plain", 
                "chars": "nys gewem\u00f0; hawia\u00f0 be gehwilcum. for \u00f0an \u00f0e oft <lb/>", 
                "language": "ang"
            }, 
            "on": "http://dms-data.stanford.edu/data/manifests/Parker/ft757ht3699/canvas/canvas-476#xywh=811,2309,2717,201"
        }, 
        {
            "@id": "_:Naa1673f7f3f340d1b1f7a129f562d3d9", 
            "@type": "oa:Annotation", 
            "motivation": "sc:painting", 
            "resource": {
                "@id": "0fcd13dbfee5314f7f78142df527f438", 
                "@type": "cnt:ContentAsText", 
                "format": "text/plain", 
                "chars": "getima\u00f0 yfelum ^m\u00e6n^ tela for life; Se heahf\u00e6der cw\u00e6\u00f0 <lb/>", 
                "language": "ang"
            }, 
            "on": "http://dms-data.stanford.edu/data/manifests/Parker/ft757ht3699/canvas/canvas-476#xywh=811,2510,2717,185"
        }, 
        {
            "@id": "_:N0154025136c541108e1f45eafa1fbc95", 
            "@type": "oa:Annotation", 
            "motivation": "sc:painting", 
            "resource": {
                "@id": "c6bf7d4ba87edb9f2cf88a1cba20e966", 
                "@type": "cnt:ContentAsText", 
                "format": "text/plain", 
                "chars": "to \u00f0am welegan; betwux us [et] eow is gef\u00e6stnod micel <lb/>", 
                "language": "ang"
            }, 
            "on": "http://dms-data.stanford.edu/data/manifests/Parker/ft757ht3699/canvas/canvas-476#xywh=811,2695,2717,196"
        }, 
        {
            "@id": "_:N044501f0e1404d4498fa7120ebe1df5d", 
            "@type": "oa:Annotation", 
            "motivation": "sc:painting", 
            "resource": {
                "@id": "dafcb2d0bbc8ad6f2c7f8a6e081fd286", 
                "@type": "cnt:ContentAsText", 
                "format": "text/plain", 
                "chars": "\u00ferosm. \u00feeah hwa wille fram us to eow he ne m\u00e6g. ne eac <lb/>", 
                "language": "ang"
            }, 
            "on": "http://dms-data.stanford.edu/data/manifests/Parker/ft757ht3699/canvas/canvas-476#xywh=811,2891,2717,190"
        }, 
        {
            "@id": "_:Nabeb5afe7e704b02a747668f6cdb07f0", 
            "@type": "oa:Annotation", 
            "motivation": "sc:painting", 
            "resource": {
                "@id": "c6b720e6698a84fb71903de6e21eaabf", 
                "@type": "cnt:ContentAsText", 
                "format": "text/plain", 
                "chars": "fram eow to us; Mid micelre geornfulnysse gewil<lb/>", 
                "language": "ang"
            }, 
            "on": "http://dms-data.stanford.edu/data/manifests/Parker/ft757ht3699/canvas/canvas-476#xywh=811,3082,2717,190"
        }, 
        {
            "@id": "_:N51c077dda5d84d43bf915380d80e3f1f", 
            "@type": "oa:Annotation", 
            "motivation": "sc:painting", 
            "resource": {
                "@id": "312cf1aa0608bd0fb9cd81898217c8aa", 
                "@type": "cnt:ContentAsText", 
                "format": "text/plain", 
                "chars": "nia\u00f0 [word erased of approx. 6-7 letters] \u00fea wi\u00f0ercor^en^an. \u00fe<\u00e6t> hi moton [moston first written, and s erased] of \u00f0\u00e6re <lb/>", 
                "language": "ang"
            }, 
            "on": "http://dms-data.stanford.edu/data/manifests/Parker/ft757ht3699/canvas/canvas-476#xywh=811,3273,2717,185"
        }, 
        {
            "@id": "_:Nc316b04f79b34d578ca9ba9e11fe4dec", 
            "@type": "oa:Annotation", 
            "motivation": "sc:painting", 
            "resource": {
                "@id": "2342e66528a9505692a6249eb77e4499", 
                "@type": "cnt:ContentAsText", 
                "format": "text/plain", 
                "chars": "susle {pinunge} \u00fee hi on cwylmia\u00f0. ac seo f\u00e6stnung \u00fe\u00e6re hel<lb/>", 
                "language": "ang"
            }, 
            "on": "http://dms-data.stanford.edu/data/manifests/Parker/ft757ht3699/canvas/canvas-476#xywh=811,3458,2717,217"
        }, 
        {
            "@id": "_:N1446be1654dd4d91ad36f0fedcc056b5", 
            "@type": "oa:Annotation", 
            "motivation": "sc:painting", 
            "resource": {
                "@id": "c10cb29939d31f11b8969b32c6ae31ce", 
                "@type": "cnt:ContentAsText", 
                "format": "text/plain", 
                "chars": "lican clysunge ne ge\u00feafa\u00f0. \u00fe<\u00e6t> hi \u00e6fre ut abrecon [e corrected from \u00e6]; <lb/>", 
                "language": "ang"
            }, 
            "on": "http://dms-data.stanford.edu/data/manifests/Parker/ft757ht3699/canvas/canvas-476#xywh=811,3676,2717,190"
        }, 
        {
            "@id": "_:Ndbe328675ea0432e9b6d643c42ba610d", 
            "@type": "oa:Annotation", 
            "motivation": "sc:painting", 
            "resource": {
                "@id": "a77f54fbed37106484ceec761710b63b", 
                "@type": "cnt:ContentAsText", 
                "format": "text/plain", 
                "chars": "eac \u00fea halgan beo\u00f0 mid heora scippendes rihtwis<lb/>", 
                "language": "ang"
            }, 
            "on": "http://dms-data.stanford.edu/data/manifests/Parker/ft757ht3699/canvas/canvas-476#xywh=811,3866,2717,196"
        }, 
        {
            "@id": "_:Nb16901b807af4c4d9d40523d0b772f32", 
            "@type": "oa:Annotation", 
            "motivation": "sc:painting", 
            "resource": {
                "@id": "6f745b96f7f1be04e33d9f4879dfc1b3", 
                "@type": "cnt:ContentAsText", 
                "format": "text/plain", 
                "chars": "nysse swa afyllede. \u00fe<\u00e6t> hi nateshwon ne besargia\u00f0 \u00fe\u00e6ra <lb/>", 
                "language": "ang"
            }, 
            "on": "http://dms-data.stanford.edu/data/manifests/Parker/ft757ht3699/canvas/canvas-476#xywh=811,4062,2717,201"
        }, 
        {
            "@id": "_:N15c2cf6dd1e640eb8e8713a50197b290", 
            "@type": "oa:Annotation", 
            "motivation": "sc:painting", 
            "resource": {
                "@id": "15774bd416167728f1025114fc3d92d2", 
                "@type": "cnt:ContentAsText", 
                "format": "text/plain", 
                "chars": "wi\u00f0ercorenra yrm\u00f0e. for \u00f0an \u00f0e hi geseo\u00f0 \u00fea for<lb/>", 
                "language": "ang"
            }, 
            "on": "http://dms-data.stanford.edu/data/manifests/Parker/ft757ht3699/canvas/canvas-476#xywh=811,4264,2717,174"
        }, 
        {
            "@id": "_:Nbacba2e7e81c4e0e9fcd45e74f28b977", 
            "@type": "oa:Annotation", 
            "motivation": "sc:painting", 
            "resource": {
                "@id": "3448a2d7ab6ac5db42e40e1ae95aaa3c", 
                "@type": "cnt:ContentAsText", 
                "format": "text/plain", 
                "chars": "donan. swa micclum fram him ge\u00e6lfremede. swa <lb/>", 
                "language": "ang"
            }, 
            "on": "http://dms-data.stanford.edu/data/manifests/Parker/ft757ht3699/canvas/canvas-476#xywh=811,4438,2717,294"
        }
    ]
}