{
  "@context": "http://www.shared-canvas.org/ns/context.json",
  "@type": "sc:AnnotationList",
  "@id": "https://dms-data.stanford.edu/data/manifests/Parker/gs233db8425/list/92v.json",
  "resources": [
    {
      "@id": "https://dms-data.stanford.edu/data/manifests/Parker/gs233db8425/annotation/5daf6bfb-79b9-4cc5-8522-1f023fa4974d",
      "@type": "oa:annotation",
      "motivation": "oa:commenting",
      "on": "https://dms-data.stanford.edu/data/manifests/Parker/gs233db8425/canvas/canvas-198#xywh=0,0,4055,6713",
      "resource": {
        "@id": "https://dms-data.stanford.edu/data/manifests/Parker/gs233db8425/res/76a3d361-38c0-4850-ae1a-0724aca298d7",
        "@type": "cnt:ContentAsText",
        "format": "text/plain",
        "chars": "Exultate. David plays on five bells. Note the very fine white ornament on the blue ground outside the letter. This is conspicuous in other places"
      }
    }
  ]
}
