{
  "@context": "http://www.shared-canvas.org/ns/context.json",
  "@type": "sc:AnnotationList",
  "@id": "https://dms-data.stanford.edu/data/manifests/Parker/nh939rq0328/list/60v.json",
  "resources": [
    {
      "@id": "https://dms-data.stanford.edu/data/manifests/Parker/nh939rq0328/annotation/8d286211-85c6-4aa0-85f3-41d7ed784747",
      "@type": "oa:Annotation",
      "motivation": "oa:commenting",
      "on": "https://dms-data.stanford.edu/data/manifests/Parker/nh939rq0328/canvas/canvas-128#xywh=0,0,5734,8502",
      "resource": {
        "@id": "https://dms-data.stanford.edu/data/manifests/Parker/nh939rq0328/res/e4e82d44-761a-4811-822d-6f590f9ff004",
        "@type": "cnt:ContentAsText",
        "format": "text/plain",
        "chars": "Explicit: That knowith (he) whom no thyng is hid fro"
      }
    },
    {
      "@id": "https://dms-data.stanford.edu/data/manifests/Parker/nh939rq0328/annotation/84b8f519-302b-4523-98ba-c9f76b26c127",
      "@type": "oa:Annotation",
      "motivation": "oa:commenting",
      "on": "https://dms-data.stanford.edu/data/manifests/Parker/nh939rq0328/canvas/canvas-128#xywh=0,0,5734,8502",
      "resource": {
        "@id": "https://dms-data.stanford.edu/data/manifests/Parker/nh939rq0328/res/eb28e3fb-cbaa-4c7f-833e-bbb6ac099f1a",
        "@type": "cnt:ContentAsText",
        "format": "text/plain",
        "chars": "Rubric: Explicit liber iste qui vocatur Occlyffe de regimine principum et constat magro Willelmo Wilflete socio aule de clare Cantabrig. qui eum scribendo propriis manibus laborauit [hic fuit Decanus de stoke college iuxta Clare added xvi]"
      }
    }
  ]
}
