{
  "@context": "http://www.shared-canvas.org/ns/context.json",
  "@type": "sc:AnnotationList",
  "@id": "https://dms-data.stanford.edu/data/manifests/Parker/fp397bs1880/list/444a.json",
  "resources": [
    {
      "@id": "https://dms-data.stanford.edu/data/manifests/Parker/fp397bs1880/annotation/061a8162-0d82-44e4-89ff-4dce2c907a25",
      "@type": "oa:Annotation",
      "motivation": "oa:commenting",
      "on": "https://dms-data.stanford.edu/data/manifests/Parker/fp397bs1880/canvas/canvas-455#xywh=0,0,6082,8873",
      "resource": {
        "@id": "https://dms-data.stanford.edu/data/manifests/Parker/fp397bs1880/res/e16d4672-35dd-4835-bc30-5ee7693ab441",
        "@type": "cnt:ContentAsText",
        "format": "text/plain",
        "chars": "Gratiam et salutem in domino foelicissimam ex animo tibi amantissime tutor exopto. Tradidi omnia que a famulo tuo acceperam Mro Cheke tui et mei atq. omnium studiosorum amicissimo pro quibus tibi a me magnas gratias agi voluit petit etiam magnopere tuae concionis exemplar ad eum quamprimo deferri quo tua etiam testificatio de integerrima vita et foelicissima morte doctoris et magistri nostri buceri ad perpetuam hominis et memorie suae commendationem posteritati tradendam"
      }
    }
  ]
}
