{
  "@context": "http://www.shared-canvas.org/ns/context.json",
  "@type": "sc:AnnotationList",
  "@id": "https://dms-data.stanford.edu/data/manifests/Parker/bt590jk0961/list/676.json",
  "resources": [
    {
      "@id": "https://dms-data.stanford.edu/data/manifests/Parker/bt590jk0961/annotation/0e170375-6615-40b8-b36d-809d355d73dd",
      "@type": "oa:annotation",
      "motivation": "oa:commenting",
      "on": "https://dms-data.stanford.edu/data/manifests/Parker/bt590jk0961/canvas/canvas-692#xywh=0,0,2515,3702",
      "resource": {
        "@id": "https://dms-data.stanford.edu/data/manifests/Parker/bt590jk0961/res/87ee1303-1097-45f7-8813-09d9de9d3d86",
        "@type": "cnt:ContentAsText",
        "format": "text/plain",
        "chars": "Incipit: Consanguinitas est uinculum diuersarum personarum carnali propagacione tractum ab eodem stipite descendencium"
      }
    }
  ]
}
