{
  "@context": "http://www.shared-canvas.org/ns/context.json",
  "@type": "sc:AnnotationList",
  "@id": "https://dms-data.stanford.edu/data/manifests/Parker/jv228wq5037/list/89.json",
  "resources": [
    {
      "@id": "https://dms-data.stanford.edu/data/manifests/Parker/jv228wq5037/annotation/e8014cfb-c33d-494e-9765-1f62854ab3fb",
      "@type": "oa:Annotation",
      "motivation": "oa:commenting",
      "on": "https://dms-data.stanford.edu/data/manifests/Parker/jv228wq5037/canvas/canvas-99#xywh=0,0,3928,5568",
      "resource": {
        "@id": "https://dms-data.stanford.edu/data/manifests/Parker/jv228wq5037/res/3ede829b-cb62-4bf6-be60-f7775acbfeb9",
        "@type": "cnt:ContentAsText",
        "format": "text/plain",
        "chars": "Incipit: Queris venerande dux Normannorum et comes andegauensium cur magistris nostri temporis minus creditur quam antiquis crederetur"
      }
    }
  ]
}
