{
  "@context": "http://www.shared-canvas.org/ns/context.json",
  "@type": "sc:AnnotationList",
  "@id": "https://dms-data.stanford.edu/data/manifests/Parker/xn117yn5845/list/230v.json",
  "resources": [
    {
      "@id": "https://dms-data.stanford.edu/data/manifests/Parker/xn117yn5845/annotation/d784e10a-05a9-40b8-a692-f50f41d3be53",
      "@type": "oa:annotation",
      "motivation": "oa:commenting",
      "on": "https://dms-data.stanford.edu/data/manifests/Parker/xn117yn5845/canvas/canvas-466#xywh=0,0,3952,6024",
      "resource": {
        "@id": "https://dms-data.stanford.edu/data/manifests/Parker/xn117yn5845/res/49128e28-3a8b-47da-8f7b-ccf1d5aafdb1",
        "@type": "cnt:ContentAsText",
        "format": "text/plain",
        "chars": "Explicit: ipso nuntiante in homine uenit. uiuens et regnans cum deo patre suo in unitate spiritu sancti unus solus et omnipotens deus per immortalia secula seculorum. Amen"
      }
    }
  ]
}
