{
  "@context": "http://www.shared-canvas.org/ns/context.json",
  "@type": "sc:AnnotationList",
  "@id": "https://dms-data.stanford.edu/data/manifests/Parker/tf043sk1517/list/3r.json",
  "resources": [
    {
      "@id": "https://dms-data.stanford.edu/data/manifests/Parker/tf043sk1517/annotation/6288b1f7-50d7-438e-8ce6-24130f058b25",
      "@type": "oa:annotation",
      "motivation": "oa:commenting",
      "on": "https://dms-data.stanford.edu/data/manifests/Parker/tf043sk1517/canvas/canvas-9#xywh=0,0,5638,8178",
      "resource": {
        "@id": "https://dms-data.stanford.edu/data/manifests/Parker/tf043sk1517/res/05fa1315-9581-48e0-b447-7d62709e0d91",
        "@type": "cnt:ContentAsText",
        "format": "text/plain",
        "chars": "Incipit: Reverendo in cristo patri patri ac dno dno dilectissimo ... alberto ... episcopo posnaniensi Nicolaus lucas ... rector parochialis ecclesiae in ganszhowa"
      }
    }
  ]
}
