{
  "@context": "http://www.shared-canvas.org/ns/context.json",
  "@type": "sc:AnnotationList",
  "@id": "https://dms-data.stanford.edu/data/manifests/Parker/qy662bj1544/list/180v.json",
  "resources": [
    {
      "@id": "https://dms-data.stanford.edu/data/manifests/Parker/qy662bj1544/annotation/eda9c9b6-b717-4b76-9bcd-e8dbcce8d47e",
      "@type": "oa:Annotation",
      "motivation": "oa:commenting",
      "on": "https://dms-data.stanford.edu/data/manifests/Parker/qy662bj1544/canvas/canvas-378#xywh=0,0,5835,8902",
      "resource": {
        "@id": "https://dms-data.stanford.edu/data/manifests/Parker/qy662bj1544/res/8554b8c0-a4b3-4f3d-a9f6-b4b3ec81403f",
        "@type": "cnt:ContentAsText",
        "format": "text/plain",
        "chars": "Esther, aAhasuerus stretches his sceptre down to b Esther, c Mordecai in broad hat, d Haman hanging. Fine work"
      }
    }
  ]
}
