{
  "@context": "http://www.shared-canvas.org/ns/context.json",
  "@type": "sc:AnnotationList",
  "@id": "https://dms-data.stanford.edu/data/manifests/Parker/nb647fd0133/list/1r.json",
  "resources": [
    {
      "@id": "https://dms-data.stanford.edu/data/manifests/Parker/nb647fd0133/annotation/6f320a39-2001-4517-9f0a-0d0a04d1274b",
      "@type": "oa:Annotation",
      "motivation": "oa:commenting",
      "on": "https://dms-data.stanford.edu/data/manifests/Parker/nb647fd0133/canvas/canvas-1#xywh=0,0,4451,6656",
      "resource": {
        "@id": "https://dms-data.stanford.edu/data/manifests/Parker/nb647fd0133/res/5483d3fd-fa2d-4b77-bebc-b515da248829",
        "@type": "cnt:ContentAsText",
        "format": "text/plain",
        "chars": "Musical notation for antiphon, verse and responsory. Begins imperfectly in antiphon for Magnificat at First Vespers for the Seventh Sunday after Pentecost: (Unxerunt Salomonem Sadoc sacerdos et Nathan pro)pheta regem in Gihon: et procedentes laeti dixerunt uiuat rex Salomon seculorum. This differs slightly from the wording of the antiphon in the 1568 editio princeps of the Breviarium Romanum"
      }
    },
    {
      "@id": "https://dms-data.stanford.edu/data/manifests/Parker/nb647fd0133/annotation/e8977721-173d-48a4-a1d0-2b94e6393e03",
      "@type": "oa:Annotation",
      "motivation": "oa:commenting",
      "on": "https://dms-data.stanford.edu/data/manifests/Parker/nb647fd0133/canvas/canvas-1#xywh=0,0,4451,6656",
      "resource": {
        "@id": "https://dms-data.stanford.edu/data/manifests/Parker/nb647fd0133/res/141c0294-ecdd-433b-af85-a21b45882c18",
        "@type": "cnt:ContentAsText",
        "format": "text/plain",
        "chars": "Rubric: Historia Salomonis Ad Vesperam"
      }
    },
    {
      "@id": "https://dms-data.stanford.edu/data/manifests/Parker/nb647fd0133/annotation/24e717b4-d98e-4d20-b4c2-1942828bcc5a",
      "@type": "oa:Annotation",
      "motivation": "oa:commenting",
      "on": "https://dms-data.stanford.edu/data/manifests/Parker/nb647fd0133/canvas/canvas-1#xywh=0,0,4451,6656",
      "resource": {
        "@id": "https://dms-data.stanford.edu/data/manifests/Parker/nb647fd0133/res/0fe1b5f2-2ba6-4b3e-b374-02ce98501d41",
        "@type": "cnt:ContentAsText",
        "format": "text/plain",
        "chars": "3-line calligraphic ornamental initial tinted in pale yellow for the versicle: Dilectio illius custodi"
      }
    }
  ]
}
